[
  { "category": "indices", "symbol": "^GSPC", "name": "S&P 500" },
  { "category": "indices", "symbol": "^IXIC", "name": "NASDAQ Composite" },
  { "category": "indices", "symbol": "^DJI", "name": "Dow Jones" },
  { "category": "indices", "symbol": "^AXJO", "name": "S&P/ASX 200" },
  { "category": "indices", "symbol": "^FTSE", "name": "FTSE 100" },
  { "category": "indices", "symbol": "^GDAXI", "name": "DAX" },
  { "category": "indices", "symbol": "^FCHI", "name": "CAC 40" },
  { "category": "indices", "symbol": "^N225", "name": "Nikkei 225" },
  { "category": "indices", "symbol": "^HSI", "name": "Hang Seng" },
  { "category": "indices", "symbol": "000001.SS", "name": "Shanghai Composite" },

  { "category": "fx", "symbol": "EURUSD=X", "name": "EUR/USD" },
  { "category": "fx", "symbol": "USDJPY=X", "name": "USD/JPY" },
  { "category": "fx", "symbol": "GBPUSD=X", "name": "GBP/USD" },
  { "category": "fx", "symbol": "USDCHF=X", "name": "USD/CHF" },
  { "category": "fx", "symbol": "AUDUSD=X", "name": "AUD/USD" },
  { "category": "fx", "symbol": "USDCAD=X", "name": "USD/CAD" },
  { "category": "fx", "symbol": "NZDUSD=X", "name": "NZD/USD" },
  { "category": "fx", "symbol": "EURGBP=X", "name": "EUR/GBP" },
  { "category": "fx", "symbol": "EURJPY=X", "name": "EUR/JPY" },
  { "category": "fx", "symbol": "GBPJPY=X", "name": "GBP/JPY" },
  { "category": "fx", "symbol": "EURCHF=X", "name": "EUR/CHF" },
  { "category": "fx", "symbol": "AUDJPY=X", "name": "AUD/JPY" },
  { "category": "fx", "symbol": "USDHKD=X", "name": "USD/HKD" },

  { "category": "commodities", "symbol": "GC=F", "name": "Gold" },
  { "category": "commodities", "symbol": "CL=F", "name": "Crude Oil WTI" },
  { "category": "commodities", "symbol": "SI=F", "name": "Silver" },
  { "category": "commodities", "symbol": "BZ=F", "name": "Brent" },
  { "category": "commodities", "symbol": "NG=F", "name": "Natural Gas" },

  { "category": "stocks", "symbol": "MSFT", "name": "Microsoft" },
  { "category": "stocks", "symbol": "AAPL", "name": "Apple" },
  { "category": "stocks", "symbol": "NVDA", "name": "NVIDIA" },
  { "category": "stocks", "symbol": "AMZN", "name": "Amazon" },

  { "category": "cryptocurrencies", "symbol": "BTC-USD", "name": "Bitcoin" },
  { "category": "cryptocurrencies", "symbol": "ETH-USD", "name": "Ethereum" },
  { "category": "cryptocurrencies", "symbol": "SOL-USD", "name": "Solana" },
  { "category": "cryptocurrencies", "symbol": "XRP-USD", "name": "XRP" }
]